classifier/ANN.py
classifier/KFold.py
classifier/__init__.py
classifier/dataset.py
classifier/evaluation.py
classifier/iris_training.py
irisClass-0.1.0.dist-info/LICENSE
irisClass-0.1.0.dist-info/METADATA
irisClass-0.1.0.dist-info/WHEEL
irisClass-0.1.0.dist-info/top_level.txt
irisClass-0.1.0.dist-info/RECORD
