Metadata-Version: 2.1
Name: irisClass
Version: 0.1.0
Summary: A demo Python project for me to understand how to create it!
Home-page: https://github.com/atikul-islam-sajib/irisClass
Author: Atikul Isla Sajib
Author-email: atikulislamsajib137@gmail.com
Project-URL: Bug Tracker, https://github.com/atikul-islam-sajib/irisClass/issues
Project-URL: Documentation, https://github.com/atikul-islam-sajib/irisClass/docs
Project-URL: Source Code, https://github.com/atikul-islam-sajib/irisClass.git
Keywords: iris classification machine-learning
Classifier: Development Status :: 3 - Alpha
Classifier: Intended Audience :: Developers
Classifier: License :: OSI Approved :: MIT License
Classifier: Programming Language :: Python :: 3
Classifier: Programming Language :: Python :: 3.6
Classifier: Programming Language :: Python :: 3.7
Classifier: Programming Language :: Python :: 3.8
Classifier: Programming Language :: Python :: 3.9
License-File: LICENSE
Requires-Dist: numpy >=1.0
Requires-Dist: torch >=1.0
Requires-Dist: scikit-learn >=0.0.1
